LICENSE
MANIFEST.in
README
setup.py
blog/__init__.py
blog/__init__.pyc
blog/admin.py
blog/feeds.py
blog/forms.py
blog/importer.py
blog/management.py
blog/models.py
blog/settings.py
blog/short_urls.py
blog/signals.py
blog/urls.py
blog/views.py
blog/migrations/0001_initial.py
blog/migrations/0002_add_category.py
blog/migrations/0003_remove_markup_type.py
blog/migrations/0004_comments.py
blog/migrations/0005_add_follows.py
blog/migrations/0006_category_renamed.py
blog/migrations/0007_creator_ip.py
blog/migrations/0008_auto__add_field_blog_icon.py
blog/migrations/0009_auto__add_field_post_rating.py
blog/migrations/0010_auto__add_field_post_votes.py
blog/migrations/0011_auto__chg_field_post_votes.py
blog/migrations/0012_auto__del_field_post_rating__del_field_post_votes.py
blog/migrations/0013_auto__add_field_blog_description.py
blog/migrations/0014_auto__del_feedlist__del_follow__del_followlist__add_bloguseraccess__ad.py
blog/migrations/0015_auto__del_field_blog_opened_blog__add_field_blog_can_read__add_field_b.py
blog/migrations/0016_auto__add_field_post_rating.py
blog/migrations/0017_auto__add_field_post_rating_score__chg_field_post_rating__add_unique_p.py
blog/migrations/0018_auto__chg_field_post_rating_score.py
blog/migrations/__init__.py
blog/static/blog.css
blog/templates/blog/base.html
blog/templates/blog/base_my.html
blog/templates/blog/base_profile.html
blog/templates/blog/blog_detail.html
blog/templates/blog/blog_list.html
blog/templates/blog/follow.html
blog/templates/blog/follow_info.html
blog/templates/blog/friends_posts.html
blog/templates/blog/post_add.html
blog/templates/blog/post_compact_iterator.html
blog/templates/blog/post_detail.html
blog/templates/blog/post_edit.html
blog/templates/blog/post_item.html
blog/templates/blog/post_iterator.html
blog/templates/blog/post_list.html
blog/templates/blog/post_my_list.html
blog/templates/blog/show_user_feed.html
blog/templates/blog/tags.html
blog/templates/blog/user_post_base_list.html
django_blogs.egg-info/PKG-INFO
django_blogs.egg-info/SOURCES.txt
django_blogs.egg-info/dependency_links.txt
django_blogs.egg-info/requires.txt
django_blogs.egg-info/top_level.txt