Metadata-Version: 1.0
Name: django-blogs
Version: 0.2.0
Summary: Django blogs - module that provide blogs to your django application.
